README.txt
ez_setup.py
setup.cfg
setup.py
python_unixtools.egg-info/PKG-INFO
python_unixtools.egg-info/SOURCES.txt
python_unixtools.egg-info/dependency_links.txt
python_unixtools.egg-info/entry_points.txt
python_unixtools.egg-info/top_level.txt
unixtools/__init__.py
unixtools/bzip2.py
unixtools/gzip.py
unixtools/tar.py